{
  "data": {
    "data": {
      "name": "Philadelphia, PA - Church Street",
      "address": {
        "street": "Church Street",
        "streetNumber": "2501",
        "city": "Philadelphia",
        "district": null,
        "state": "PA",
        "countryCode": "US",
        "country": "United States",
        "postalCode": "19124",
        "postalExt": null,
        "navRegion": "us",
        "nearestEntrance": null
      },
      "entryPoint": {
        "latitude": 40.002285,
        "longitude": -75.081643
      },
      "centroid": {
        "latitude": 40.00203,
        "longitude": -75.081665
      },
      "publicStallCount": 8,
      "openToPublic": true,
      "amenities": [
        "AMENITIES_WIFI",
        "AMENITIES_RESTROOMS",
        "AMENITIES_CAFE",
        "AMENITIES_SHOPPING",
        "AMENITIES_RESTAURANT",
        "AMENITIES_TWENTY_FOUR_HOUR"
      ],
      "maxPowerKw": 250,
      "timeZone": "America/New_York",
      "accessType": "Public",
      "openToNonTeslas": false,
      "availabilityProfile": {
        "siteId": {
          "id": 2767,
          "siteType": "SITE_TYPE_SUPERCHARGER"
        },
        "trtId": {
          "id": 7097,
          "siteType": "SITE_TYPE_SUPERCHARGER"
        },
        "createdTimestamp": "2026-06-02T00:00:00Z",
        "utcOffset": "-14400s",
        "availabilityProfile": {
          "sunday": {
            "congestionValue": [
              0.5,
              0.4641544117647059,
              0.5688100961538461,
              0.6953125,
              0.6334134615384615,
              0.5227272727272727,
              0.4453125,
              0.4453125,
              0.375,
              0.310546875,
              0.310546875,
              0.3581730769230769,
              0.3515625,
              0.33293269230769235,
              0.318359375,
              0.404296875,
              0.4751838235294118,
              0.53125,
              0.5390625,
              0.55625,
              0.5625,
              0.5375,
              0.5271381578947368,
              0.528125
            ]
          },
          "monday": {
            "congestionValue": [
              0.463125,
              0.375,
              0.421875,
              0.49375,
              0.51875,
              0.4556818181818182,
              0.3404411764705882,
              0.25156249999999997,
              0.20625,
              0.27749999999999997,
              0.3991071428571428,
              0.475,
              0.4476190476190476,
              0.4072368421052631,
              0.41118421052631576,
              0.4896739130434782,
              0.55,
              0.5959134615384615,
              0.6433035714285713,
              0.6625,
              0.6142857142857143,
              0.5770833333333334,
              0.58125,
              0.5375651041666666
            ]
          },
          "tuesday": {
            "congestionValue": [
              0.4507133152173913,
              0.38341346153846156,
              0.4498355263157895,
              0.54453125,
              0.5703125,
              0.48828125,
              0.39787946428571425,
              0.33473557692307687,
              0.30965909090909094,
              0.3347355769230769,
              0.4473684210526316,
              0.4375,
              0.38692434210526316,
              0.2651375205254516,
              0.3625391200294551,
              0.45466753774680607,
              0.49972098214285715,
              0.5191536901218821,
              0.5387834821428572,
              0.5234375,
              0.5060763888888888,
              0.515625,
              0.5394965277777778,
              0.5
            ]
          },
          "wednesday": {
            "congestionValue": [
              0.4641544117647059,
              0.4453125,
              0.5461956521739131,
              0.5859375,
              0.5213994565217391,
              0.43125,
              0.4140625,
              0.3536458333333333,
              0.3229166666666667,
              0.3571428571428571,
              0.421875,
              0.4140625,
              0.3722098214285714,
              0.36177884615384615,
              0.41552734375,
              0.4913194444444444,
              0.5625,
              0.6015625,
              0.585546875,
              0.53125,
              0.5036764705882353,
              0.4765625,
              0.5032894736842105,
              0.5234375
            ]
          },
          "thursday": {
            "congestionValue": [
              0.5398848684210527,
              0.46691176470588236,
              0.5901442307692308,
              0.6875,
              0.7325721153846154,
              0.5725,
              0.40625,
              0.3203125,
              0.3216145833333333,
              0.40811820652173914,
              0.5252511160714286,
              0.525390625,
              0.515625,
              0.421875,
              0.4947916666666667,
              0.5078125,
              0.546875,
              0.5546875,
              0.546875,
              0.484375,
              0.4255514705882353,
              0.38341346153846156,
              0.4352022058823529,
              0.4921875
            ]
          },
          "friday": {
            "congestionValue": [
              0.49172794117647056,
              0.4638671875,
              0.5305397727272727,
              0.6385869565217391,
              0.65625,
              0.5509510869565217,
              0.3759765625,
              0.3231026785714286,
              0.271484375,
              0.375,
              0.46875,
              0.55390625,
              0.5390625,
              0.50234375,
              0.421875,
              0.39501953125,
              0.459077380952381,
              0.5625,
              0.5680803571428572,
              0.4375,
              0.3872767857142857,
              0.4279513888888889,
              0.5453125,
              0.59375
            ]
          },
          "saturday": {
            "congestionValue": [
              0.55390625,
              0.49609375,
              0.5529891304347826,
              0.6328125,
              0.6338315217391304,
              0.5796875,
              0.5707236842105263,
              0.546875,
              0.4078947368421053,
              0.2979910714285714,
              0.2890625,
              0.4007352941176471,
              0.453125,
              0.4967105263157895,
              0.5234375,
              0.5625,
              0.5254934210526316,
              0.540234375,
              0.6164772727272727,
              0.6328125,
              0.5791903409090909,
              0.5582031249999999,
              0.5625,
              0.517578125
            ]
          }
        }
      },
      "accessHours": {
        "twentyFourSeven": true
      },
      "locationGUID": "dcbdabdb-9e02-4168-88c0-f51e7b119e97",
      "commonSiteName": "Royal Farms",
      "ownershipType": null,
      "brandName": null,
      "effectivePricebooks": [
        {
          "feeType": "CHARGING",
          "rateBase": 0.45,
          "rateTier1": 0,
          "rateTier2": 0,
          "rateMinTier1": null,
          "rateMinTier2": null,
          "rateMinTier3": null,
          "rateMinTier4": null,
          "currencyCode": "USD",
          "uom": "kwh",
          "startTime": "",
          "endTime": "",
          "days": "",
          "isTou": false,
          "vehicleMakeType": "TSLA",
          "minSiteOccupancy": null,
          "maxSiteOccupancy": null,
          "isMemberPricebook": true
        },
        {
          "feeType": "CHARGING",
          "rateBase": 0.43,
          "rateTier1": 0,
          "rateTier2": 0,
          "rateMinTier1": null,
          "rateMinTier2": null,
          "rateMinTier3": null,
          "rateMinTier4": null,
          "currencyCode": "USD",
          "uom": "kwh",
          "startTime": "08:00",
          "endTime": "23:00",
          "days": "0,1,2,3,4,5,6",
          "isTou": true,
          "vehicleMakeType": "TSLA",
          "minSiteOccupancy": null,
          "maxSiteOccupancy": null,
          "isMemberPricebook": true
        },
        {
          "feeType": "CHARGING",
          "rateBase": 0.24,
          "rateTier1": 0,
          "rateTier2": 0,
          "rateMinTier1": null,
          "rateMinTier2": null,
          "rateMinTier3": null,
          "rateMinTier4": null,
          "currencyCode": "USD",
          "uom": "kwh",
          "startTime": "04:00",
          "endTime": "08:00",
          "days": "0,1,2,3,4,5,6",
          "isTou": true,
          "vehicleMakeType": "TSLA",
          "minSiteOccupancy": null,
          "maxSiteOccupancy": null,
          "isMemberPricebook": true
        },
        {
          "feeType": "CHARGING",
          "rateBase": 0.24,
          "rateTier1": 0,
          "rateTier2": 0,
          "rateMinTier1": null,
          "rateMinTier2": null,
          "rateMinTier3": null,
          "rateMinTier4": null,
          "currencyCode": "USD",
          "uom": "kwh",
          "startTime": "23:00",
          "endTime": "00:00",
          "days": "0,1,2,3,4,5,6",
          "isTou": true,
          "vehicleMakeType": "TSLA",
          "minSiteOccupancy": null,
          "maxSiteOccupancy": null,
          "isMemberPricebook": true
        },
        {
          "feeType": "CHARGING",
          "rateBase": 0.24,
          "rateTier1": 0,
          "rateTier2": 0,
          "rateMinTier1": null,
          "rateMinTier2": null,
          "rateMinTier3": null,
          "rateMinTier4": null,
          "currencyCode": "USD",
          "uom": "kwh",
          "startTime": "00:00",
          "endTime": "04:00",
          "days": "0,1,2,3,4,5,6",
          "isTou": true,
          "vehicleMakeType": "TSLA",
          "minSiteOccupancy": null,
          "maxSiteOccupancy": null,
          "isMemberPricebook": true
        },
        {
          "feeType": "CONGESTION",
          "rateBase": 0.5,
          "rateTier1": 0,
          "rateTier2": 0,
          "rateMinTier1": null,
          "rateMinTier2": null,
          "rateMinTier3": null,
          "rateMinTier4": null,
          "currencyCode": "USD",
          "uom": "min",
          "startTime": "",
          "endTime": "",
          "days": "",
          "isTou": false,
          "vehicleMakeType": "TSLA",
          "minSiteOccupancy": null,
          "maxSiteOccupancy": null,
          "isMemberPricebook": true
        },
        {
          "feeType": "CHARGING",
          "rateBase": 0.63,
          "rateTier1": 0,
          "rateTier2": 0,
          "rateMinTier1": null,
          "rateMinTier2": null,
          "rateMinTier3": null,
          "rateMinTier4": null,
          "currencyCode": "USD",
          "uom": "kwh",
          "startTime": "",
          "endTime": "",
          "days": "",
          "isTou": false,
          "vehicleMakeType": "NTSLA",
          "minSiteOccupancy": null,
          "maxSiteOccupancy": null,
          "isMemberPricebook": false
        },
        {
          "feeType": "CHARGING",
          "rateBase": 0.6,
          "rateTier1": 0,
          "rateTier2": 0,
          "rateMinTier1": null,
          "rateMinTier2": null,
          "rateMinTier3": null,
          "rateMinTier4": null,
          "currencyCode": "USD",
          "uom": "kwh",
          "startTime": "08:00",
          "endTime": "23:00",
          "days": "0,1,2,3,4,5,6",
          "isTou": true,
          "vehicleMakeType": "NTSLA",
          "minSiteOccupancy": null,
          "maxSiteOccupancy": null,
          "isMemberPricebook": false
        },
        {
          "feeType": "CHARGING",
          "rateBase": 0.34,
          "rateTier1": 0,
          "rateTier2": 0,
          "rateMinTier1": null,
          "rateMinTier2": null,
          "rateMinTier3": null,
          "rateMinTier4": null,
          "currencyCode": "USD",
          "uom": "kwh",
          "startTime": "04:00",
          "endTime": "08:00",
          "days": "0,1,2,3,4,5,6",
          "isTou": true,
          "vehicleMakeType": "NTSLA",
          "minSiteOccupancy": null,
          "maxSiteOccupancy": null,
          "isMemberPricebook": false
        },
        {
          "feeType": "CHARGING",
          "rateBase": 0.34,
          "rateTier1": 0,
          "rateTier2": 0,
          "rateMinTier1": null,
          "rateMinTier2": null,
          "rateMinTier3": null,
          "rateMinTier4": null,
          "currencyCode": "USD",
          "uom": "kwh",
          "startTime": "23:00",
          "endTime": "00:00",
          "days": "0,1,2,3,4,5,6",
          "isTou": true,
          "vehicleMakeType": "NTSLA",
          "minSiteOccupancy": null,
          "maxSiteOccupancy": null,
          "isMemberPricebook": false
        },
        {
          "feeType": "CHARGING",
          "rateBase": 0.34,
          "rateTier1": 0,
          "rateTier2": 0,
          "rateMinTier1": null,
          "rateMinTier2": null,
          "rateMinTier3": null,
          "rateMinTier4": null,
          "currencyCode": "USD",
          "uom": "kwh",
          "startTime": "00:00",
          "endTime": "04:00",
          "days": "0,1,2,3,4,5,6",
          "isTou": true,
          "vehicleMakeType": "NTSLA",
          "minSiteOccupancy": null,
          "maxSiteOccupancy": null,
          "isMemberPricebook": false
        },
        {
          "feeType": "CONGESTION",
          "rateBase": 0.5,
          "rateTier1": 0,
          "rateTier2": 0,
          "rateMinTier1": null,
          "rateMinTier2": null,
          "rateMinTier3": null,
          "rateMinTier4": null,
          "currencyCode": "USD",
          "uom": "min",
          "startTime": "",
          "endTime": "",
          "days": "",
          "isTou": false,
          "vehicleMakeType": "NTSLA",
          "minSiteOccupancy": null,
          "maxSiteOccupancy": null,
          "isMemberPricebook": false
        }
      ],
      "isTrailerFriendly": false
    },
    "success": true
  }
}