{
  "data": {
    "data": {
      "name": "Burlington, ON",
      "address": {
        "street": "Maple Avenue",
        "streetNumber": "900",
        "city": "Burlington",
        "district": null,
        "state": "ON",
        "countryCode": "CA",
        "country": "Canada",
        "postalCode": "L7S 2J8",
        "postalExt": null,
        "navRegion": "us",
        "nearestEntrance": null
      },
      "entryPoint": {
        "latitude": 43.326276,
        "longitude": -79.822231
      },
      "centroid": {
        "latitude": 43.326261,
        "longitude": -79.822276
      },
      "publicStallCount": 16,
      "openToPublic": true,
      "amenities": [
        "AMENITIES_WIFI",
        "AMENITIES_RESTROOMS",
        "AMENITIES_CAFE",
        "AMENITIES_SHOPPING",
        "AMENITIES_RESTAURANT"
      ],
      "maxPowerKw": 150,
      "timeZone": "America/Toronto",
      "accessType": "Public",
      "openToNonTeslas": false,
      "availabilityProfile": {
        "siteId": {
          "id": 1738,
          "siteType": "SITE_TYPE_SUPERCHARGER"
        },
        "trtId": {
          "id": 3459,
          "siteType": "SITE_TYPE_SUPERCHARGER"
        },
        "createdTimestamp": "2026-06-02T00:00:00Z",
        "utcOffset": "-14400s",
        "availabilityProfile": {
          "sunday": {
            "congestionValue": [
              0.25040849673202614,
              0.2552083333333333,
              0.24209126759678232,
              0.22161153426497127,
              0.20025355175021609,
              0.14926314756671902,
              0.1311829068926962,
              0.10825892857142856,
              0.12196928879310345,
              0.1255580357142857,
              0.1255580357142857,
              0.1402930040687161,
              0.16792719414893614,
              0.2447167787569573,
              0.319375,
              0.4104042658730158,
              0.5371447921273772,
              0.6391741071428572,
              0.6774237431023912,
              0.6721354166666667,
              0.609320979375298,
              0.4708237044817927,
              0.34305555555555556,
              0.27890624999999997
            ]
          },
          "monday": {
            "congestionValue": [
              0.274375,
              0.26303008595988536,
              0.20090136054421767,
              0.16170335591133003,
              0.14393770292207791,
              0.13526785714285713,
              0.10219155844155843,
              0.08688186813186813,
              0.09910714285714284,
              0.10559065934065935,
              0.11964285714285716,
              0.1294642857142857,
              0.1437025075987842,
              0.17136292016806726,
              0.25021263851452535,
              0.32792259203227436,
              0.36169642857142853,
              0.3648403963262454,
              0.36196428571428574,
              0.3296838945221695,
              0.34476042447926947,
              0.3794345238095238,
              0.3915167633784655,
              0.36369628906250007
            ]
          },
          "tuesday": {
            "congestionValue": [
              0.3346354166666667,
              0.27965188746438746,
              0.20101250804375803,
              0.1819828308207705,
              0.15885416666666666,
              0.1437290619765494,
              0.09401041666666667,
              0.07980158730158729,
              0.06786805555555556,
              0.09628193430656934,
              0.1378042912137681,
              0.16770833333333332,
              0.18699376947040497,
              0.20543518518518517,
              0.2552083333333333,
              0.3125,
              0.38197544642857145,
              0.40234375,
              0.3911830357142857,
              0.34375,
              0.3158052884615385,
              0.292289402173913,
              0.34716796875,
              0.34765625
            ]
          },
          "wednesday": {
            "congestionValue": [
              0.2666015625,
              0.205078125,
              0.15234375,
              0.14985795454545453,
              0.12890625,
              0.095703125,
              0.08370535714285714,
              0.0859375,
              0.10498046875,
              0.13020833333333334,
              0.1875,
              0.21484375,
              0.207763671875,
              0.207763671875,
              0.2878605769230769,
              0.3515625,
              0.3911830357142857,
              0.40234375,
              0.3819754464285714,
              0.35,
              0.359375,
              0.39814814814814814,
              0.40625,
              0.3836805555555555
            ]
          },
          "thursday": {
            "congestionValue": [
              0.34716796875,
              0.2831182065217391,
              0.20888157894736842,
              0.1830357142857143,
              0.19140625,
              0.16517857142857142,
              0.1337890625,
              0.09375,
              0.09319196428571427,
              0.11647727272727273,
              0.15234375,
              0.1640625,
              0.177734375,
              0.22916666666666669,
              0.30078125,
              0.3366168478260869,
              0.37823275862068967,
              0.390625,
              0.35240917487684725,
              0.3418675206363033,
              0.40421013911182446,
              0.44003906249999997,
              0.41596397012105407,
              0.40373826399116347
            ]
          },
          "friday": {
            "congestionValue": [
              0.3827380952380952,
              0.3254897929962363,
              0.2410922366828087,
              0.19819084311806917,
              0.1612209530164379,
              0.1385952877879491,
              0.11004191343622877,
              0.08820975971033576,
              0.12743108851368637,
              0.15967261904761904,
              0.15969020666593572,
              0.19193424823633154,
              0.21145833333333333,
              0.24507295296167245,
              0.26066747095950293,
              0.30764100868267535,
              0.3614469282238443,
              0.39661458333333327,
              0.3834245742092457,
              0.3846316425120773,
              0.42638888888888893,
              0.46145833333333336,
              0.43191105145762,
              0.38245346078772413
            ]
          },
          "saturday": {
            "congestionValue": [
              0.3325892857142857,
              0.3097306177905945,
              0.2767857142857143,
              0.2619321165966386,
              0.22488839285714288,
              0.1593806749394673,
              0.12220982142857142,
              0.11357445520581112,
              0.11886160714285714,
              0.09944385593220338,
              0.10588304924242424,
              0.12667410714285715,
              0.1643562030075188,
              0.2156991332116788,
              0.31738782051282055,
              0.4181341853666245,
              0.4978268365272938,
              0.5503148320895521,
              0.6031279961649089,
              0.6520491803278688,
              0.6690848214285714,
              0.5976086797423887,
              0.48967685557569585,
              0.40270205066006004
            ]
          }
        }
      },
      "accessHours": {
        "twentyFourSeven": true
      },
      "locationGUID": "3cff6db2-c154-4968-9af1-644725d25a8e",
      "commonSiteName": "Mapleview Centre",
      "ownershipType": null,
      "brandName": null,
      "effectivePricebooks": [
        {
          "feeType": "CHARGING",
          "rateBase": 0.41,
          "rateTier1": 0,
          "rateTier2": 0,
          "rateMinTier1": null,
          "rateMinTier2": null,
          "rateMinTier3": null,
          "rateMinTier4": null,
          "currencyCode": "CAD",
          "uom": "kwh",
          "startTime": "",
          "endTime": "",
          "days": "",
          "isTou": false,
          "vehicleMakeType": "TSLA",
          "minSiteOccupancy": null,
          "maxSiteOccupancy": null,
          "isMemberPricebook": true
        },
        {
          "feeType": "CHARGING",
          "rateBase": 0.51,
          "rateTier1": 0,
          "rateTier2": 0,
          "rateMinTier1": null,
          "rateMinTier2": null,
          "rateMinTier3": null,
          "rateMinTier4": null,
          "currencyCode": "CAD",
          "uom": "kwh",
          "startTime": "12:00",
          "endTime": "20:00",
          "days": "0,1,2,3,4,5,6",
          "isTou": true,
          "vehicleMakeType": "TSLA",
          "minSiteOccupancy": null,
          "maxSiteOccupancy": null,
          "isMemberPricebook": true
        },
        {
          "feeType": "CHARGING",
          "rateBase": 0.39,
          "rateTier1": 0,
          "rateTier2": 0,
          "rateMinTier1": null,
          "rateMinTier2": null,
          "rateMinTier3": null,
          "rateMinTier4": null,
          "currencyCode": "CAD",
          "uom": "kwh",
          "startTime": "08:00",
          "endTime": "12:00",
          "days": "0,1,2,3,4,5,6",
          "isTou": true,
          "vehicleMakeType": "TSLA",
          "minSiteOccupancy": null,
          "maxSiteOccupancy": null,
          "isMemberPricebook": true
        },
        {
          "feeType": "CHARGING",
          "rateBase": 0.28,
          "rateTier1": 0,
          "rateTier2": 0,
          "rateMinTier1": null,
          "rateMinTier2": null,
          "rateMinTier3": null,
          "rateMinTier4": null,
          "currencyCode": "CAD",
          "uom": "kwh",
          "startTime": "04:00",
          "endTime": "08:00",
          "days": "0,1,2,3,4,5,6",
          "isTou": true,
          "vehicleMakeType": "TSLA",
          "minSiteOccupancy": null,
          "maxSiteOccupancy": null,
          "isMemberPricebook": true
        },
        {
          "feeType": "CHARGING",
          "rateBase": 0.39,
          "rateTier1": 0,
          "rateTier2": 0,
          "rateMinTier1": null,
          "rateMinTier2": null,
          "rateMinTier3": null,
          "rateMinTier4": null,
          "currencyCode": "CAD",
          "uom": "kwh",
          "startTime": "20:00",
          "endTime": "00:00",
          "days": "0,1,2,3,4,5,6",
          "isTou": true,
          "vehicleMakeType": "TSLA",
          "minSiteOccupancy": null,
          "maxSiteOccupancy": null,
          "isMemberPricebook": true
        },
        {
          "feeType": "CHARGING",
          "rateBase": 0.28,
          "rateTier1": 0,
          "rateTier2": 0,
          "rateMinTier1": null,
          "rateMinTier2": null,
          "rateMinTier3": null,
          "rateMinTier4": null,
          "currencyCode": "CAD",
          "uom": "kwh",
          "startTime": "00:00",
          "endTime": "04:00",
          "days": "0,1,2,3,4,5,6",
          "isTou": true,
          "vehicleMakeType": "TSLA",
          "minSiteOccupancy": null,
          "maxSiteOccupancy": null,
          "isMemberPricebook": true
        },
        {
          "feeType": "CONGESTION",
          "rateBase": 0.5,
          "rateTier1": 0,
          "rateTier2": 0,
          "rateMinTier1": null,
          "rateMinTier2": null,
          "rateMinTier3": null,
          "rateMinTier4": null,
          "currencyCode": "CAD",
          "uom": "min",
          "startTime": "",
          "endTime": "",
          "days": "",
          "isTou": false,
          "vehicleMakeType": "TSLA",
          "minSiteOccupancy": null,
          "maxSiteOccupancy": null,
          "isMemberPricebook": true
        },
        {
          "feeType": "CHARGING",
          "rateBase": 0.58,
          "rateTier1": 0,
          "rateTier2": 0,
          "rateMinTier1": null,
          "rateMinTier2": null,
          "rateMinTier3": null,
          "rateMinTier4": null,
          "currencyCode": "CAD",
          "uom": "kwh",
          "startTime": "",
          "endTime": "",
          "days": "",
          "isTou": false,
          "vehicleMakeType": "NTSLA",
          "minSiteOccupancy": null,
          "maxSiteOccupancy": null,
          "isMemberPricebook": false
        },
        {
          "feeType": "CHARGING",
          "rateBase": 0.72,
          "rateTier1": 0,
          "rateTier2": 0,
          "rateMinTier1": null,
          "rateMinTier2": null,
          "rateMinTier3": null,
          "rateMinTier4": null,
          "currencyCode": "CAD",
          "uom": "kwh",
          "startTime": "12:00",
          "endTime": "20:00",
          "days": "0,1,2,3,4,5,6",
          "isTou": true,
          "vehicleMakeType": "NTSLA",
          "minSiteOccupancy": null,
          "maxSiteOccupancy": null,
          "isMemberPricebook": false
        },
        {
          "feeType": "CHARGING",
          "rateBase": 0.54,
          "rateTier1": 0,
          "rateTier2": 0,
          "rateMinTier1": null,
          "rateMinTier2": null,
          "rateMinTier3": null,
          "rateMinTier4": null,
          "currencyCode": "CAD",
          "uom": "kwh",
          "startTime": "08:00",
          "endTime": "12:00",
          "days": "0,1,2,3,4,5,6",
          "isTou": true,
          "vehicleMakeType": "NTSLA",
          "minSiteOccupancy": null,
          "maxSiteOccupancy": null,
          "isMemberPricebook": false
        },
        {
          "feeType": "CHARGING",
          "rateBase": 0.39,
          "rateTier1": 0,
          "rateTier2": 0,
          "rateMinTier1": null,
          "rateMinTier2": null,
          "rateMinTier3": null,
          "rateMinTier4": null,
          "currencyCode": "CAD",
          "uom": "kwh",
          "startTime": "04:00",
          "endTime": "08:00",
          "days": "0,1,2,3,4,5,6",
          "isTou": true,
          "vehicleMakeType": "NTSLA",
          "minSiteOccupancy": null,
          "maxSiteOccupancy": null,
          "isMemberPricebook": false
        },
        {
          "feeType": "CHARGING",
          "rateBase": 0.54,
          "rateTier1": 0,
          "rateTier2": 0,
          "rateMinTier1": null,
          "rateMinTier2": null,
          "rateMinTier3": null,
          "rateMinTier4": null,
          "currencyCode": "CAD",
          "uom": "kwh",
          "startTime": "20:00",
          "endTime": "00:00",
          "days": "0,1,2,3,4,5,6",
          "isTou": true,
          "vehicleMakeType": "NTSLA",
          "minSiteOccupancy": null,
          "maxSiteOccupancy": null,
          "isMemberPricebook": false
        },
        {
          "feeType": "CHARGING",
          "rateBase": 0.39,
          "rateTier1": 0,
          "rateTier2": 0,
          "rateMinTier1": null,
          "rateMinTier2": null,
          "rateMinTier3": null,
          "rateMinTier4": null,
          "currencyCode": "CAD",
          "uom": "kwh",
          "startTime": "00:00",
          "endTime": "04:00",
          "days": "0,1,2,3,4,5,6",
          "isTou": true,
          "vehicleMakeType": "NTSLA",
          "minSiteOccupancy": null,
          "maxSiteOccupancy": null,
          "isMemberPricebook": false
        },
        {
          "feeType": "CONGESTION",
          "rateBase": 0.5,
          "rateTier1": 0,
          "rateTier2": 0,
          "rateMinTier1": null,
          "rateMinTier2": null,
          "rateMinTier3": null,
          "rateMinTier4": null,
          "currencyCode": "CAD",
          "uom": "min",
          "startTime": "",
          "endTime": "",
          "days": "",
          "isTou": false,
          "vehicleMakeType": "NTSLA",
          "minSiteOccupancy": null,
          "maxSiteOccupancy": null,
          "isMemberPricebook": false
        }
      ],
      "isTrailerFriendly": false
    },
    "success": true
  }
}