{
  "data": {
    "data": {
      "name": "New River, AZ",
      "address": {
        "street": "West New River Road",
        "streetNumber": "3906",
        "city": "New River",
        "district": null,
        "state": "AZ",
        "countryCode": "US",
        "country": "United States",
        "postalCode": "85087",
        "postalExt": null,
        "navRegion": "us",
        "nearestEntrance": null
      },
      "entryPoint": {
        "latitude": 33.915754,
        "longitude": -112.144203
      },
      "centroid": {
        "latitude": 33.915762,
        "longitude": -112.144192
      },
      "publicStallCount": 10,
      "openToPublic": true,
      "amenities": [
        "AMENITIES_RESTROOMS",
        "AMENITIES_CAFE",
        "AMENITIES_RESTAURANT",
        "AMENITIES_TWENTY_FOUR_HOUR"
      ],
      "maxPowerKw": 150,
      "timeZone": "America/Phoenix",
      "accessType": "Public",
      "openToNonTeslas": false,
      "availabilityProfile": {
        "siteId": {
          "id": 2272,
          "siteType": "SITE_TYPE_SUPERCHARGER"
        },
        "trtId": {
          "id": 8836,
          "siteType": "SITE_TYPE_SUPERCHARGER"
        },
        "createdTimestamp": "2026-06-02T00:00:00Z",
        "utcOffset": "-25200s",
        "availabilityProfile": {
          "sunday": {
            "congestionValue": [
              0.29508547008547004,
              0.33402777777777776,
              0.33125,
              0.257031857031857,
              0.18506944444444445,
              0.16527777777777777,
              0.16810312024353122,
              0.1215277777777778,
              0.08411458333333335,
              0.013888888888888888,
              0.05,
              0.07801932367149758,
              0.14607407407407408,
              0.19234437751004013,
              0.22563657407407406,
              0.2680894308943089,
              0.3382735583684951,
              0.416829561042524,
              0.46825396825396826,
              0.49375,
              0.5105113636363636,
              0.49999999999999994,
              0.4710227272727272,
              0.42625
            ]
          },
          "monday": {
            "congestionValue": [
              0.3828888888888889,
              0.35473684210526313,
              0.33,
              0.2536842105263158,
              0.15416666666666665,
              0.09428571428571429,
              0.053750000000000006,
              0.036666666666666674,
              0.02,
              0.02,
              0.03666666666666667,
              0.05,
              0.07400000000000001,
              0.12250000000000003,
              0.21411764705882352,
              0.29000000000000004,
              0.32705256154357953,
              0.32555555555555554,
              0.3291284098469727,
              0.33760233918128657,
              0.3716666666666667,
              0.37000000000000005,
              0.356578947368421,
              0.34
            ]
          },
          "tuesday": {
            "congestionValue": [
              0.28833333333333333,
              0.2416666666666667,
              0.20000000000000004,
              0.17500000000000002,
              0.16562500000000002,
              0.17500000000000002,
              0.1421875,
              0.084375,
              0.03541666666666667,
              0.025,
              0.0125,
              0.05,
              0.05937500000000001,
              0.1,
              0.1421875,
              0.2,
              0.2677884615384616,
              0.30625,
              0.30673076923076925,
              0.3,
              0.33125,
              0.36250000000000004,
              0.35,
              0.2857142857142857
            ]
          },
          "wednesday": {
            "congestionValue": [
              0.2778846153846154,
              0.24375000000000002,
              0.19567307692307692,
              0.146875,
              0.15625,
              0.15078125,
              0.10625,
              0.08000000000000002,
              0.05,
              0.043750000000000004,
              0.043750000000000004,
              0.0375,
              0.06875,
              0.13,
              0.19999999999999998,
              0.21500000000000002,
              0.25357142857142856,
              0.3,
              0.3285714285714286,
              0.325,
              0.37697368421052635,
              0.375,
              0.34210526315789475,
              0.29017857142857145
            ]
          },
          "thursday": {
            "congestionValue": [
              0.30624999999999997,
              0.24999999999999997,
              0.185,
              0.1375,
              0.09166666666666667,
              0.07968750000000002,
              0.043750000000000004,
              0.05,
              0.018750000000000003,
              0.025,
              0.025,
              0.034375,
              0.05937500000000001,
              0.12916666666666668,
              0.1975,
              0.25,
              0.25625,
              0.23238636363636364,
              0.2733333333333333,
              0.3400735294117647,
              0.375,
              0.3172794117647059,
              0.2901785714285714,
              0.32499999999999996
            ]
          },
          "friday": {
            "congestionValue": [
              0.325,
              0.29017857142857145,
              0.25625000000000003,
              0.23977272727272728,
              0.19375,
              0.15833333333333335,
              0.10625,
              0.075,
              0.03541666666666667,
              0.025,
              0.018750000000000003,
              0.025,
              0.10703125,
              0.1681818181818182,
              0.25625,
              0.28177083333333336,
              0.31500000000000006,
              0.3375,
              0.40714285714285714,
              0.44930555555555557,
              0.4775205761316873,
              0.45555555555555555,
              0.49765625,
              0.5284722222222222
            ]
          },
          "saturday": {
            "congestionValue": [
              0.468312757201646,
              0.3701428345959596,
              0.2951388888888889,
              0.2783283283283283,
              0.2548611111111111,
              0.1868124312431243,
              0.12707382039573822,
              0.05625000000000001,
              0.037500000000000006,
              0.0125,
              0.018750000000000003,
              0.04583333333333333,
              0.084375,
              0.14218750000000002,
              0.2259615384615385,
              0.30375,
              0.368359375,
              0.4377834467120182,
              0.5264135802469136,
              0.5895833333333333,
              0.5471172839506173,
              0.49405446086480576,
              0.4666666666666666,
              0.45543785310734464
            ]
          }
        }
      },
      "accessHours": {
        "twentyFourSeven": true
      },
      "locationGUID": "b97243e5-be86-4b0b-b02a-b97dd0b55be0",
      "commonSiteName": "Shell",
      "ownershipType": null,
      "brandName": null,
      "effectivePricebooks": [
        {
          "feeType": "CHARGING",
          "rateBase": 0.43,
          "rateTier1": 0,
          "rateTier2": 0,
          "rateMinTier1": null,
          "rateMinTier2": null,
          "rateMinTier3": null,
          "rateMinTier4": null,
          "currencyCode": "USD",
          "uom": "kwh",
          "startTime": "",
          "endTime": "",
          "days": "",
          "isTou": false,
          "vehicleMakeType": "TSLA",
          "minSiteOccupancy": null,
          "maxSiteOccupancy": null,
          "isMemberPricebook": true
        },
        {
          "feeType": "CHARGING",
          "rateBase": 0.5,
          "rateTier1": 0,
          "rateTier2": 0,
          "rateMinTier1": null,
          "rateMinTier2": null,
          "rateMinTier3": null,
          "rateMinTier4": null,
          "currencyCode": "USD",
          "uom": "kwh",
          "startTime": "11:00",
          "endTime": "19:00",
          "days": "0,1,2,3,4,5,6",
          "isTou": true,
          "vehicleMakeType": "TSLA",
          "minSiteOccupancy": null,
          "maxSiteOccupancy": null,
          "isMemberPricebook": true
        },
        {
          "feeType": "CHARGING",
          "rateBase": 0.39,
          "rateTier1": 0,
          "rateTier2": 0,
          "rateMinTier1": null,
          "rateMinTier2": null,
          "rateMinTier3": null,
          "rateMinTier4": null,
          "currencyCode": "USD",
          "uom": "kwh",
          "startTime": "19:00",
          "endTime": "23:00",
          "days": "0,1,2,3,4,5,6",
          "isTou": true,
          "vehicleMakeType": "TSLA",
          "minSiteOccupancy": null,
          "maxSiteOccupancy": null,
          "isMemberPricebook": true
        },
        {
          "feeType": "CHARGING",
          "rateBase": 0.39,
          "rateTier1": 0,
          "rateTier2": 0,
          "rateMinTier1": null,
          "rateMinTier2": null,
          "rateMinTier3": null,
          "rateMinTier4": null,
          "currencyCode": "USD",
          "uom": "kwh",
          "startTime": "04:00",
          "endTime": "11:00",
          "days": "0,1,2,3,4,5,6",
          "isTou": true,
          "vehicleMakeType": "TSLA",
          "minSiteOccupancy": null,
          "maxSiteOccupancy": null,
          "isMemberPricebook": true
        },
        {
          "feeType": "CHARGING",
          "rateBase": 0.33,
          "rateTier1": 0,
          "rateTier2": 0,
          "rateMinTier1": null,
          "rateMinTier2": null,
          "rateMinTier3": null,
          "rateMinTier4": null,
          "currencyCode": "USD",
          "uom": "kwh",
          "startTime": "23:00",
          "endTime": "00:00",
          "days": "0,1,2,3,4,5,6",
          "isTou": true,
          "vehicleMakeType": "TSLA",
          "minSiteOccupancy": null,
          "maxSiteOccupancy": null,
          "isMemberPricebook": true
        },
        {
          "feeType": "CHARGING",
          "rateBase": 0.33,
          "rateTier1": 0,
          "rateTier2": 0,
          "rateMinTier1": null,
          "rateMinTier2": null,
          "rateMinTier3": null,
          "rateMinTier4": null,
          "currencyCode": "USD",
          "uom": "kwh",
          "startTime": "00:00",
          "endTime": "04:00",
          "days": "0,1,2,3,4,5,6",
          "isTou": true,
          "vehicleMakeType": "TSLA",
          "minSiteOccupancy": null,
          "maxSiteOccupancy": null,
          "isMemberPricebook": true
        },
        {
          "feeType": "CONGESTION",
          "rateBase": 0.5,
          "rateTier1": 0,
          "rateTier2": 0,
          "rateMinTier1": null,
          "rateMinTier2": null,
          "rateMinTier3": null,
          "rateMinTier4": null,
          "currencyCode": "USD",
          "uom": "min",
          "startTime": "",
          "endTime": "",
          "days": "",
          "isTou": false,
          "vehicleMakeType": "TSLA",
          "minSiteOccupancy": null,
          "maxSiteOccupancy": null,
          "isMemberPricebook": true
        },
        {
          "feeType": "CHARGING",
          "rateBase": 0.6,
          "rateTier1": 0,
          "rateTier2": 0,
          "rateMinTier1": null,
          "rateMinTier2": null,
          "rateMinTier3": null,
          "rateMinTier4": null,
          "currencyCode": "USD",
          "uom": "kwh",
          "startTime": "",
          "endTime": "",
          "days": "",
          "isTou": false,
          "vehicleMakeType": "NTSLA",
          "minSiteOccupancy": null,
          "maxSiteOccupancy": null,
          "isMemberPricebook": false
        },
        {
          "feeType": "CHARGING",
          "rateBase": 0.7,
          "rateTier1": 0,
          "rateTier2": 0,
          "rateMinTier1": null,
          "rateMinTier2": null,
          "rateMinTier3": null,
          "rateMinTier4": null,
          "currencyCode": "USD",
          "uom": "kwh",
          "startTime": "11:00",
          "endTime": "19:00",
          "days": "0,1,2,3,4,5,6",
          "isTou": true,
          "vehicleMakeType": "NTSLA",
          "minSiteOccupancy": null,
          "maxSiteOccupancy": null,
          "isMemberPricebook": false
        },
        {
          "feeType": "CHARGING",
          "rateBase": 0.55,
          "rateTier1": 0,
          "rateTier2": 0,
          "rateMinTier1": null,
          "rateMinTier2": null,
          "rateMinTier3": null,
          "rateMinTier4": null,
          "currencyCode": "USD",
          "uom": "kwh",
          "startTime": "19:00",
          "endTime": "23:00",
          "days": "0,1,2,3,4,5,6",
          "isTou": true,
          "vehicleMakeType": "NTSLA",
          "minSiteOccupancy": null,
          "maxSiteOccupancy": null,
          "isMemberPricebook": false
        },
        {
          "feeType": "CHARGING",
          "rateBase": 0.55,
          "rateTier1": 0,
          "rateTier2": 0,
          "rateMinTier1": null,
          "rateMinTier2": null,
          "rateMinTier3": null,
          "rateMinTier4": null,
          "currencyCode": "USD",
          "uom": "kwh",
          "startTime": "04:00",
          "endTime": "11:00",
          "days": "0,1,2,3,4,5,6",
          "isTou": true,
          "vehicleMakeType": "NTSLA",
          "minSiteOccupancy": null,
          "maxSiteOccupancy": null,
          "isMemberPricebook": false
        },
        {
          "feeType": "CHARGING",
          "rateBase": 0.47,
          "rateTier1": 0,
          "rateTier2": 0,
          "rateMinTier1": null,
          "rateMinTier2": null,
          "rateMinTier3": null,
          "rateMinTier4": null,
          "currencyCode": "USD",
          "uom": "kwh",
          "startTime": "23:00",
          "endTime": "00:00",
          "days": "0,1,2,3,4,5,6",
          "isTou": true,
          "vehicleMakeType": "NTSLA",
          "minSiteOccupancy": null,
          "maxSiteOccupancy": null,
          "isMemberPricebook": false
        },
        {
          "feeType": "CHARGING",
          "rateBase": 0.47,
          "rateTier1": 0,
          "rateTier2": 0,
          "rateMinTier1": null,
          "rateMinTier2": null,
          "rateMinTier3": null,
          "rateMinTier4": null,
          "currencyCode": "USD",
          "uom": "kwh",
          "startTime": "00:00",
          "endTime": "04:00",
          "days": "0,1,2,3,4,5,6",
          "isTou": true,
          "vehicleMakeType": "NTSLA",
          "minSiteOccupancy": null,
          "maxSiteOccupancy": null,
          "isMemberPricebook": false
        },
        {
          "feeType": "CONGESTION",
          "rateBase": 0.5,
          "rateTier1": 0,
          "rateTier2": 0,
          "rateMinTier1": null,
          "rateMinTier2": null,
          "rateMinTier3": null,
          "rateMinTier4": null,
          "currencyCode": "USD",
          "uom": "min",
          "startTime": "",
          "endTime": "",
          "days": "",
          "isTou": false,
          "vehicleMakeType": "NTSLA",
          "minSiteOccupancy": null,
          "maxSiteOccupancy": null,
          "isMemberPricebook": false
        }
      ],
      "isTrailerFriendly": false
    },
    "success": true
  }
}