{
  "data": {
    "data": {
      "name": "New York, NY - W 75th Street",
      "address": {
        "street": "W 75th Street",
        "streetNumber": "201",
        "city": "New York",
        "district": null,
        "state": "NY",
        "countryCode": "US",
        "country": "United States",
        "postalCode": "10023",
        "postalExt": "1704",
        "navRegion": "us",
        "nearestEntrance": null
      },
      "entryPoint": {
        "latitude": 40.780903,
        "longitude": -73.980092
      },
      "centroid": {
        "latitude": 40.780954,
        "longitude": -73.980467
      },
      "publicStallCount": 4,
      "openToPublic": true,
      "amenities": [
        "AMENITIES_WIFI",
        "AMENITIES_RESTROOMS",
        "AMENITIES_CAFE",
        "AMENITIES_SHOPPING",
        "AMENITIES_LODGING",
        "AMENITIES_RESTAURANT",
        "AMENITIES_TWENTY_FOUR_HOUR"
      ],
      "maxPowerKw": 72,
      "timeZone": "America/New_York",
      "accessType": "Public",
      "openToNonTeslas": false,
      "availabilityProfile": {
        "siteId": {
          "id": 1367,
          "siteType": "SITE_TYPE_SUPERCHARGER"
        },
        "trtId": {
          "id": 4159,
          "siteType": "SITE_TYPE_SUPERCHARGER"
        },
        "createdTimestamp": "2026-06-02T00:00:00Z",
        "utcOffset": "-14400s",
        "availabilityProfile": {
          "sunday": {
            "congestionValue": [
              0.296875,
              0.25,
              0.20703125,
              0.15625,
              0.08854166666666667,
              0.03125,
              0,
              0,
              0,
              0,
              0.03125,
              0.03125,
              0.03125,
              0.0625,
              0.10416666666666666,
              0.20937499999999998,
              0.28125,
              0.33072916666666663,
              0.375,
              0.4375,
              0.51875,
              0.53125,
              0.440625,
              0.3270833333333333
            ]
          },
          "monday": {
            "congestionValue": [
              0.33515625,
              0.36250000000000004,
              0.3359375,
              0.28214285714285714,
              0.2,
              0.14,
              0.05,
              0.05,
              0.05,
              0.05,
              0.05,
              0.1645833333333333,
              0.253125,
              0.36250000000000004,
              0.3078125,
              0.22857142857142854,
              0.13749999999999998,
              0.13333333333333333,
              0.1875,
              0.2625,
              0.2875,
              0.2982142857142857,
              0.3,
              0.30223214285714284
            ]
          },
          "tuesday": {
            "congestionValue": [
              0.265625,
              0.253125,
              0.234375,
              0.25,
              0.234375,
              0.16796875,
              0.11458333333333334,
              0.0625,
              0.0625,
              0.0625,
              0.0625,
              0.11458333333333334,
              0.15625,
              0.2578125,
              0.3125,
              0.2942708333333333,
              0.20937499999999998,
              0.1953125,
              0.203125,
              0.253125,
              0.25,
              0.33482142857142855,
              0.34375,
              0.3526785714285714
            ]
          },
          "wednesday": {
            "congestionValue": [
              0.296875,
              0.26875,
              0.203125,
              0.171875,
              0.09375,
              0.0625,
              0.03125,
              0,
              0,
              0,
              0,
              0.03125,
              0.1171875,
              0.203125,
              0.25,
              0.25,
              0.25,
              0.21875,
              0.1953125,
              0.140625,
              0.140625,
              0.203125,
              0.3125,
              0.39285714285714285
            ]
          },
          "thursday": {
            "congestionValue": [
              0.40625,
              0.4107142857142857,
              0.34375,
              0.2589285714285714,
              0.109375,
              0.0625,
              0.03125,
              0,
              0,
              0.03125,
              0.146875,
              0.25,
              0.296875,
              0.26875,
              0.21875,
              0.25,
              0.265625,
              0.3526785714285714,
              0.390625,
              0.33928571428571425,
              0.1875,
              0.1875,
              0.125,
              0.1953125
            ]
          },
          "friday": {
            "congestionValue": [
              0.203125,
              0.20703125,
              0.1875,
              0.1875,
              0.1875,
              0.1875,
              0.1875,
              0.1875,
              0.171875,
              0.14583333333333331,
              0.14583333333333334,
              0.1875,
              0.2708333333333333,
              0.34375,
              0.328125,
              0.28125,
              0.21875,
              0.2265625,
              0.203125,
              0.21875,
              0.21875,
              0.25,
              0.26875,
              0.28125
            ]
          },
          "saturday": {
            "congestionValue": [
              0.25,
              0.16796875,
              0.08854166666666667,
              0.03125,
              0,
              0,
              0,
              0,
              0,
              0.03125,
              0.08854166666666667,
              0.16796875,
              0.203125,
              0.171875,
              0.125,
              0.2,
              0.25,
              0.25,
              0.2265625,
              0.203125,
              0.25,
              0.265625,
              0.3526785714285714,
              0.40625
            ]
          }
        }
      },
      "accessHours": {
        "regularHours": [
          {
            "weekday": 7,
            "periodBegin": "06:00",
            "periodEnd": "23:59"
          },
          {
            "weekday": 1,
            "periodBegin": "06:00",
            "periodEnd": "23:59"
          },
          {
            "weekday": 2,
            "periodBegin": "06:00",
            "periodEnd": "23:59"
          },
          {
            "weekday": 3,
            "periodBegin": "06:00",
            "periodEnd": "23:59"
          },
          {
            "weekday": 4,
            "periodBegin": "06:00",
            "periodEnd": "23:59"
          },
          {
            "weekday": 5,
            "periodBegin": "06:00",
            "periodEnd": "23:59"
          },
          {
            "weekday": 6,
            "periodBegin": "06:00",
            "periodEnd": "23:59"
          }
        ],
        "twentyFourSeven": false
      },
      "locationGUID": "056957b2-0e8e-42cb-b694-d7e941739647",
      "commonSiteName": "Champion park",
      "ownershipType": null,
      "brandName": null,
      "effectivePricebooks": [
        {
          "feeType": "CHARGING",
          "rateBase": 0.41,
          "rateTier1": 0,
          "rateTier2": 0,
          "rateMinTier1": null,
          "rateMinTier2": null,
          "rateMinTier3": null,
          "rateMinTier4": null,
          "currencyCode": "USD",
          "uom": "kwh",
          "startTime": "",
          "endTime": "",
          "days": "",
          "isTou": false,
          "vehicleMakeType": "TSLA",
          "minSiteOccupancy": null,
          "maxSiteOccupancy": null,
          "isMemberPricebook": true
        },
        {
          "feeType": "CHARGING",
          "rateBase": 0.4,
          "rateTier1": 0,
          "rateTier2": 0,
          "rateMinTier1": null,
          "rateMinTier2": null,
          "rateMinTier3": null,
          "rateMinTier4": null,
          "currencyCode": "USD",
          "uom": "kwh",
          "startTime": "08:00",
          "endTime": "23:00",
          "days": "0,1,2,3,4,5,6",
          "isTou": true,
          "vehicleMakeType": "TSLA",
          "minSiteOccupancy": null,
          "maxSiteOccupancy": null,
          "isMemberPricebook": true
        },
        {
          "feeType": "CHARGING",
          "rateBase": 0.35,
          "rateTier1": 0,
          "rateTier2": 0,
          "rateMinTier1": null,
          "rateMinTier2": null,
          "rateMinTier3": null,
          "rateMinTier4": null,
          "currencyCode": "USD",
          "uom": "kwh",
          "startTime": "04:00",
          "endTime": "08:00",
          "days": "0,1,2,3,4,5,6",
          "isTou": true,
          "vehicleMakeType": "TSLA",
          "minSiteOccupancy": null,
          "maxSiteOccupancy": null,
          "isMemberPricebook": true
        },
        {
          "feeType": "CHARGING",
          "rateBase": 0.35,
          "rateTier1": 0,
          "rateTier2": 0,
          "rateMinTier1": null,
          "rateMinTier2": null,
          "rateMinTier3": null,
          "rateMinTier4": null,
          "currencyCode": "USD",
          "uom": "kwh",
          "startTime": "23:00",
          "endTime": "00:00",
          "days": "0,1,2,3,4,5,6",
          "isTou": true,
          "vehicleMakeType": "TSLA",
          "minSiteOccupancy": null,
          "maxSiteOccupancy": null,
          "isMemberPricebook": true
        },
        {
          "feeType": "CHARGING",
          "rateBase": 0.35,
          "rateTier1": 0,
          "rateTier2": 0,
          "rateMinTier1": null,
          "rateMinTier2": null,
          "rateMinTier3": null,
          "rateMinTier4": null,
          "currencyCode": "USD",
          "uom": "kwh",
          "startTime": "00:00",
          "endTime": "04:00",
          "days": "0,1,2,3,4,5,6",
          "isTou": true,
          "vehicleMakeType": "TSLA",
          "minSiteOccupancy": null,
          "maxSiteOccupancy": null,
          "isMemberPricebook": true
        },
        {
          "feeType": "PARKING",
          "rateBase": 0,
          "rateTier1": 0,
          "rateTier2": 0,
          "rateMinTier1": null,
          "rateMinTier2": null,
          "rateMinTier3": null,
          "rateMinTier4": null,
          "currencyCode": "USD",
          "uom": "min",
          "startTime": "",
          "endTime": "",
          "days": "",
          "isTou": false,
          "vehicleMakeType": "TSLA",
          "minSiteOccupancy": null,
          "maxSiteOccupancy": null,
          "isMemberPricebook": true
        },
        {
          "feeType": "CHARGING",
          "rateBase": 0.57,
          "rateTier1": 0,
          "rateTier2": 0,
          "rateMinTier1": null,
          "rateMinTier2": null,
          "rateMinTier3": null,
          "rateMinTier4": null,
          "currencyCode": "USD",
          "uom": "kwh",
          "startTime": "",
          "endTime": "",
          "days": "",
          "isTou": false,
          "vehicleMakeType": "NTSLA",
          "minSiteOccupancy": null,
          "maxSiteOccupancy": null,
          "isMemberPricebook": false
        },
        {
          "feeType": "CHARGING",
          "rateBase": 0.56,
          "rateTier1": 0,
          "rateTier2": 0,
          "rateMinTier1": null,
          "rateMinTier2": null,
          "rateMinTier3": null,
          "rateMinTier4": null,
          "currencyCode": "USD",
          "uom": "kwh",
          "startTime": "08:00",
          "endTime": "23:00",
          "days": "0,1,2,3,4,5,6",
          "isTou": true,
          "vehicleMakeType": "NTSLA",
          "minSiteOccupancy": null,
          "maxSiteOccupancy": null,
          "isMemberPricebook": false
        },
        {
          "feeType": "CHARGING",
          "rateBase": 0.49,
          "rateTier1": 0,
          "rateTier2": 0,
          "rateMinTier1": null,
          "rateMinTier2": null,
          "rateMinTier3": null,
          "rateMinTier4": null,
          "currencyCode": "USD",
          "uom": "kwh",
          "startTime": "04:00",
          "endTime": "08:00",
          "days": "0,1,2,3,4,5,6",
          "isTou": true,
          "vehicleMakeType": "NTSLA",
          "minSiteOccupancy": null,
          "maxSiteOccupancy": null,
          "isMemberPricebook": false
        },
        {
          "feeType": "CHARGING",
          "rateBase": 0.49,
          "rateTier1": 0,
          "rateTier2": 0,
          "rateMinTier1": null,
          "rateMinTier2": null,
          "rateMinTier3": null,
          "rateMinTier4": null,
          "currencyCode": "USD",
          "uom": "kwh",
          "startTime": "23:00",
          "endTime": "00:00",
          "days": "0,1,2,3,4,5,6",
          "isTou": true,
          "vehicleMakeType": "NTSLA",
          "minSiteOccupancy": null,
          "maxSiteOccupancy": null,
          "isMemberPricebook": false
        },
        {
          "feeType": "CHARGING",
          "rateBase": 0.49,
          "rateTier1": 0,
          "rateTier2": 0,
          "rateMinTier1": null,
          "rateMinTier2": null,
          "rateMinTier3": null,
          "rateMinTier4": null,
          "currencyCode": "USD",
          "uom": "kwh",
          "startTime": "00:00",
          "endTime": "04:00",
          "days": "0,1,2,3,4,5,6",
          "isTou": true,
          "vehicleMakeType": "NTSLA",
          "minSiteOccupancy": null,
          "maxSiteOccupancy": null,
          "isMemberPricebook": false
        },
        {
          "feeType": "PARKING",
          "rateBase": 0,
          "rateTier1": 0,
          "rateTier2": 0,
          "rateMinTier1": null,
          "rateMinTier2": null,
          "rateMinTier3": null,
          "rateMinTier4": null,
          "currencyCode": "USD",
          "uom": "min",
          "startTime": "",
          "endTime": "",
          "days": "",
          "isTou": false,
          "vehicleMakeType": "NTSLA",
          "minSiteOccupancy": null,
          "maxSiteOccupancy": null,
          "isMemberPricebook": false
        }
      ],
      "isTrailerFriendly": false
    },
    "success": true
  }
}