{
  "data": {
    "data": {
      "name": "Pendleton, OR",
      "address": {
        "street": "Wildhorse Blvd.",
        "streetNumber": "46510",
        "city": "Pendleton",
        "district": null,
        "state": "OR",
        "countryCode": "US",
        "country": "United States",
        "postalCode": "97801",
        "postalExt": "6043",
        "navRegion": "us",
        "nearestEntrance": null
      },
      "entryPoint": {
        "latitude": 45.646494,
        "longitude": -118.681805
      },
      "centroid": {
        "latitude": 45.646557,
        "longitude": -118.682182
      },
      "publicStallCount": 8,
      "openToPublic": true,
      "amenities": [
        "AMENITIES_WIFI",
        "AMENITIES_RESTROOMS",
        "AMENITIES_CAFE",
        "AMENITIES_LODGING",
        "AMENITIES_RESTAURANT",
        "AMENITIES_TWENTY_FOUR_HOUR"
      ],
      "maxPowerKw": 150,
      "timeZone": "America/Los_Angeles",
      "accessType": "Public",
      "openToNonTeslas": false,
      "availabilityProfile": {
        "siteId": {
          "id": 558,
          "siteType": "SITE_TYPE_SUPERCHARGER"
        },
        "trtId": {
          "id": 2457,
          "siteType": "SITE_TYPE_SUPERCHARGER"
        },
        "createdTimestamp": "2026-06-02T00:00:00Z",
        "utcOffset": "-25200s",
        "availabilityProfile": {
          "sunday": {
            "congestionValue": [
              0.4765625,
              0.4007352941176471,
              0.3627232142857143,
              0.375,
              0.3236607142857143,
              0.2326388888888889,
              0.134765625,
              0.09375,
              0.0234375,
              0.03125,
              0.04296875,
              0.0625,
              0.09375,
              0.109375,
              0.18489583333333334,
              0.251953125,
              0.39522058823529405,
              0.503228939476554,
              0.5989317602040816,
              0.6227678571428572,
              0.6079545454545454,
              0.59375,
              0.57734375,
              0.5247258771929825
            ]
          },
          "monday": {
            "congestionValue": [
              0.5004032258064517,
              0.5083333333333333,
              0.4829301075268817,
              0.3595628415300547,
              0.2552517361111111,
              0.15625,
              0.1713333333333333,
              0.19374999999999998,
              0.22325268817204297,
              0.21249999999999997,
              0.17553763440860215,
              0.11875,
              0.10750000000000001,
              0.11666666666666667,
              0.1706989247311828,
              0.2505589430894309,
              0.3467767295597484,
              0.42007575757575755,
              0.48563112745098036,
              0.5642708333333333,
              0.5875,
              0.51625,
              0.4517241379310345,
              0.4722562056737589
            ]
          },
          "tuesday": {
            "congestionValue": [
              0.4697916666666666,
              0.38375443262411346,
              0.3235677083333333,
              0.26822916666666663,
              0.255298132183908,
              0.18840579710144925,
              0.12097537878787878,
              0.03125,
              0.046875,
              0.03125,
              0.06770833333333333,
              0.05468749999999999,
              0.09575320512820512,
              0.109375,
              0.11758814102564101,
              0.18283045977011494,
              0.25260416666666663,
              0.29889112903225806,
              0.30729166666666663,
              0.30485551075268813,
              0.2781968390804597,
              0.3672916666666666,
              0.3984375,
              0.37476934523809524
            ]
          },
          "wednesday": {
            "congestionValue": [
              0.3484468005952381,
              0.36979166666666663,
              0.34035528273809523,
              0.2728494623655914,
              0.21989583333333332,
              0.18568840579710144,
              0.16145833333333331,
              0.19044384057971014,
              0.23061342592592593,
              0.23958333333333331,
              0.17881944444444445,
              0.11562499999999999,
              0.09375,
              0.12890625,
              0.1328125,
              0.1579861111111111,
              0.15340909090909088,
              0.23576388888888888,
              0.32589285714285715,
              0.3723958333333333,
              0.3702876984126984,
              0.3333333333333333,
              0.31333705357142855,
              0.32461734693877553
            ]
          },
          "thursday": {
            "congestionValue": [
              0.34598214285714285,
              0.3425480769230769,
              0.296875,
              0.2872362012987013,
              0.2421875,
              0.17370129870129872,
              0.10205853174603174,
              0.07291666666666667,
              0.0859375,
              0.09375,
              0.078125,
              0.08333333333333334,
              0.0625,
              0.13151041666666666,
              0.21153846153846154,
              0.3125,
              0.3581730769230769,
              0.3671875,
              0.4239583333333333,
              0.46588541666666666,
              0.5266812865497076,
              0.5487351190476191,
              0.5581893762939959,
              0.5334821428571428
            ]
          },
          "friday": {
            "congestionValue": [
              0.4373786878881988,
              0.2738695276497696,
              0.22395833333333334,
              0.20543411330049255,
              0.2553146258503401,
              0.26004464285714285,
              0.2092013888888889,
              0.18239795918367346,
              0.15848214285714285,
              0.1581187707641196,
              0.1484375,
              0.16536458333333331,
              0.1796875,
              0.1796875,
              0.19921875,
              0.2716346153846154,
              0.3671875,
              0.44485294117647056,
              0.53125,
              0.609375,
              0.59375,
              0.5226151315789473,
              0.52890625,
              0.5985054347826088
            ]
          },
          "saturday": {
            "congestionValue": [
              0.6875,
              0.6513975155279502,
              0.5289888682745825,
              0.3853332820197044,
              0.287297549833887,
              0.2219611528822055,
              0.19785714285714284,
              0.1640625,
              0.140625,
              0.109375,
              0.09375,
              0.1167953667953668,
              0.1523765756302521,
              0.20982142857142858,
              0.28605693922305764,
              0.3553407843633907,
              0.4360517644557823,
              0.5451281055900621,
              0.59375,
              0.5896739130434783,
              0.5234375,
              0.48766447368421056,
              0.45263671875,
              0.4765625
            ]
          }
        }
      },
      "accessHours": {
        "twentyFourSeven": true
      },
      "locationGUID": "965c0827-ac0e-499a-a6aa-9a8e5697780e",
      "commonSiteName": "Wildhorse Resort & Casino",
      "ownershipType": null,
      "brandName": null,
      "effectivePricebooks": [
        {
          "feeType": "CHARGING",
          "rateBase": 0.38,
          "rateTier1": 0,
          "rateTier2": 0,
          "rateMinTier1": null,
          "rateMinTier2": null,
          "rateMinTier3": null,
          "rateMinTier4": null,
          "currencyCode": "USD",
          "uom": "kwh",
          "startTime": "",
          "endTime": "",
          "days": "",
          "isTou": false,
          "vehicleMakeType": "TSLA",
          "minSiteOccupancy": null,
          "maxSiteOccupancy": null,
          "isMemberPricebook": true
        },
        {
          "feeType": "CHARGING",
          "rateBase": 0.36,
          "rateTier1": 0,
          "rateTier2": 0,
          "rateMinTier1": null,
          "rateMinTier2": null,
          "rateMinTier3": null,
          "rateMinTier4": null,
          "currencyCode": "USD",
          "uom": "kwh",
          "startTime": "04:00",
          "endTime": "12:00",
          "days": "0,1,2,3,4,5,6",
          "isTou": true,
          "vehicleMakeType": "TSLA",
          "minSiteOccupancy": null,
          "maxSiteOccupancy": null,
          "isMemberPricebook": true
        },
        {
          "feeType": "CHARGING",
          "rateBase": 0.36,
          "rateTier1": 0,
          "rateTier2": 0,
          "rateMinTier1": null,
          "rateMinTier2": null,
          "rateMinTier3": null,
          "rateMinTier4": null,
          "currencyCode": "USD",
          "uom": "kwh",
          "startTime": "20:00",
          "endTime": "00:00",
          "days": "0,1,2,3,4,5,6",
          "isTou": true,
          "vehicleMakeType": "TSLA",
          "minSiteOccupancy": null,
          "maxSiteOccupancy": null,
          "isMemberPricebook": true
        },
        {
          "feeType": "CHARGING",
          "rateBase": 0.5,
          "rateTier1": 0,
          "rateTier2": 0,
          "rateMinTier1": null,
          "rateMinTier2": null,
          "rateMinTier3": null,
          "rateMinTier4": null,
          "currencyCode": "USD",
          "uom": "kwh",
          "startTime": "12:00",
          "endTime": "16:00",
          "days": "0,1,2,3,4,5,6",
          "isTou": true,
          "vehicleMakeType": "TSLA",
          "minSiteOccupancy": null,
          "maxSiteOccupancy": null,
          "isMemberPricebook": true
        },
        {
          "feeType": "CHARGING",
          "rateBase": 0.42,
          "rateTier1": 0,
          "rateTier2": 0,
          "rateMinTier1": null,
          "rateMinTier2": null,
          "rateMinTier3": null,
          "rateMinTier4": null,
          "currencyCode": "USD",
          "uom": "kwh",
          "startTime": "16:00",
          "endTime": "20:00",
          "days": "0,1,2,3,4,5,6",
          "isTou": true,
          "vehicleMakeType": "TSLA",
          "minSiteOccupancy": null,
          "maxSiteOccupancy": null,
          "isMemberPricebook": true
        },
        {
          "feeType": "CHARGING",
          "rateBase": 0.36,
          "rateTier1": 0,
          "rateTier2": 0,
          "rateMinTier1": null,
          "rateMinTier2": null,
          "rateMinTier3": null,
          "rateMinTier4": null,
          "currencyCode": "USD",
          "uom": "kwh",
          "startTime": "00:00",
          "endTime": "04:00",
          "days": "0,1,2,3,4,5,6",
          "isTou": true,
          "vehicleMakeType": "TSLA",
          "minSiteOccupancy": null,
          "maxSiteOccupancy": null,
          "isMemberPricebook": true
        },
        {
          "feeType": "CONGESTION",
          "rateBase": 0.5,
          "rateTier1": 0,
          "rateTier2": 0,
          "rateMinTier1": null,
          "rateMinTier2": null,
          "rateMinTier3": null,
          "rateMinTier4": null,
          "currencyCode": "USD",
          "uom": "min",
          "startTime": "",
          "endTime": "",
          "days": "",
          "isTou": false,
          "vehicleMakeType": "TSLA",
          "minSiteOccupancy": null,
          "maxSiteOccupancy": null,
          "isMemberPricebook": true
        },
        {
          "feeType": "CHARGING",
          "rateBase": 0.53,
          "rateTier1": 0,
          "rateTier2": 0,
          "rateMinTier1": null,
          "rateMinTier2": null,
          "rateMinTier3": null,
          "rateMinTier4": null,
          "currencyCode": "USD",
          "uom": "kwh",
          "startTime": "",
          "endTime": "",
          "days": "",
          "isTou": false,
          "vehicleMakeType": "NTSLA",
          "minSiteOccupancy": null,
          "maxSiteOccupancy": null,
          "isMemberPricebook": false
        },
        {
          "feeType": "CHARGING",
          "rateBase": 0.5,
          "rateTier1": 0,
          "rateTier2": 0,
          "rateMinTier1": null,
          "rateMinTier2": null,
          "rateMinTier3": null,
          "rateMinTier4": null,
          "currencyCode": "USD",
          "uom": "kwh",
          "startTime": "04:00",
          "endTime": "12:00",
          "days": "0,1,2,3,4,5,6",
          "isTou": true,
          "vehicleMakeType": "NTSLA",
          "minSiteOccupancy": null,
          "maxSiteOccupancy": null,
          "isMemberPricebook": false
        },
        {
          "feeType": "CHARGING",
          "rateBase": 0.5,
          "rateTier1": 0,
          "rateTier2": 0,
          "rateMinTier1": null,
          "rateMinTier2": null,
          "rateMinTier3": null,
          "rateMinTier4": null,
          "currencyCode": "USD",
          "uom": "kwh",
          "startTime": "20:00",
          "endTime": "00:00",
          "days": "0,1,2,3,4,5,6",
          "isTou": true,
          "vehicleMakeType": "NTSLA",
          "minSiteOccupancy": null,
          "maxSiteOccupancy": null,
          "isMemberPricebook": false
        },
        {
          "feeType": "CHARGING",
          "rateBase": 0.71,
          "rateTier1": 0,
          "rateTier2": 0,
          "rateMinTier1": null,
          "rateMinTier2": null,
          "rateMinTier3": null,
          "rateMinTier4": null,
          "currencyCode": "USD",
          "uom": "kwh",
          "startTime": "12:00",
          "endTime": "16:00",
          "days": "0,1,2,3,4,5,6",
          "isTou": true,
          "vehicleMakeType": "NTSLA",
          "minSiteOccupancy": null,
          "maxSiteOccupancy": null,
          "isMemberPricebook": false
        },
        {
          "feeType": "CHARGING",
          "rateBase": 0.59,
          "rateTier1": 0,
          "rateTier2": 0,
          "rateMinTier1": null,
          "rateMinTier2": null,
          "rateMinTier3": null,
          "rateMinTier4": null,
          "currencyCode": "USD",
          "uom": "kwh",
          "startTime": "16:00",
          "endTime": "20:00",
          "days": "0,1,2,3,4,5,6",
          "isTou": true,
          "vehicleMakeType": "NTSLA",
          "minSiteOccupancy": null,
          "maxSiteOccupancy": null,
          "isMemberPricebook": false
        },
        {
          "feeType": "CHARGING",
          "rateBase": 0.5,
          "rateTier1": 0,
          "rateTier2": 0,
          "rateMinTier1": null,
          "rateMinTier2": null,
          "rateMinTier3": null,
          "rateMinTier4": null,
          "currencyCode": "USD",
          "uom": "kwh",
          "startTime": "00:00",
          "endTime": "04:00",
          "days": "0,1,2,3,4,5,6",
          "isTou": true,
          "vehicleMakeType": "NTSLA",
          "minSiteOccupancy": null,
          "maxSiteOccupancy": null,
          "isMemberPricebook": false
        },
        {
          "feeType": "CONGESTION",
          "rateBase": 0.5,
          "rateTier1": 0,
          "rateTier2": 0,
          "rateMinTier1": null,
          "rateMinTier2": null,
          "rateMinTier3": null,
          "rateMinTier4": null,
          "currencyCode": "USD",
          "uom": "min",
          "startTime": "",
          "endTime": "",
          "days": "",
          "isTou": false,
          "vehicleMakeType": "NTSLA",
          "minSiteOccupancy": null,
          "maxSiteOccupancy": null,
          "isMemberPricebook": false
        }
      ],
      "isTrailerFriendly": false
    },
    "success": true
  }
}