{
  "data": {
    "data": {
      "name": "Truckee, CA - Donner Pass Road",
      "address": {
        "street": "Donner Pass Rd",
        "streetNumber": "11290",
        "city": "Truckee",
        "district": null,
        "state": "CA",
        "countryCode": "US",
        "country": "United States",
        "postalCode": "96161",
        "postalExt": "4808",
        "navRegion": "us",
        "nearestEntrance": null
      },
      "entryPoint": {
        "latitude": 39.327438,
        "longitude": -120.20741
      },
      "centroid": {
        "latitude": 39.327444,
        "longitude": -120.20741
      },
      "publicStallCount": 11,
      "openToPublic": true,
      "amenities": [
        "AMENITIES_WIFI",
        "AMENITIES_RESTROOMS",
        "AMENITIES_CAFE",
        "AMENITIES_SHOPPING",
        "AMENITIES_RESTAURANT"
      ],
      "maxPowerKw": 150,
      "timeZone": "America/Los_Angeles",
      "accessType": "Public",
      "openToNonTeslas": false,
      "availabilityProfile": {
        "siteId": {
          "id": 190,
          "siteType": "SITE_TYPE_SUPERCHARGER"
        },
        "trtId": {
          "id": 2219,
          "siteType": "SITE_TYPE_SUPERCHARGER"
        },
        "createdTimestamp": "2026-06-02T00:00:00Z",
        "utcOffset": "-25200s",
        "availabilityProfile": {
          "sunday": {
            "congestionValue": [
              0.14828629032258064,
              0.17763671874999998,
              0.16857638888888887,
              0.12825038580246914,
              0.06666666666666667,
              0.04846743295019157,
              0.025,
              0.02576388888888889,
              0.020138888888888887,
              0.013888888888888888,
              0,
              0,
              0.0125,
              0.04817942942942943,
              0.08333333333333333,
              0.16636377068557923,
              0.2152777777777778,
              0.278833559168925,
              0.3201546717171717,
              0.3458333333333333,
              0.3260416666666667,
              0.3104166666666667,
              0.29375,
              0.25368258477633476
            ]
          },
          "monday": {
            "congestionValue": [
              0.1825013299135556,
              0.13343333043906108,
              0.10085326570175054,
              0.11419191919191919,
              0.08563164108618652,
              0.04525728987993139,
              0.042222222222222223,
              0.03777777777777778,
              0.030498084291187735,
              0.01111111111111111,
              0,
              0,
              0.03111111111111111,
              0.07783347727585646,
              0.13328282828282828,
              0.1499008674101611,
              0.1577864498112878,
              0.18719046223004004,
              0.21988375544555322,
              0.23207070707070707,
              0.23187719895585066,
              0.21474747474747474,
              0.19086784071077267,
              0.19880820619301254
            ]
          },
          "tuesday": {
            "congestionValue": [
              0.20314393939393938,
              0.1643299303862859,
              0.09250000000000001,
              0.05,
              0.03636363636363636,
              0.011363636363636364,
              0.011363636363636364,
              0,
              0,
              0.0125,
              0.0125,
              0.0125,
              0,
              0.023863636363636365,
              0.06862571022727273,
              0.12145316804407716,
              0.1634012539184953,
              0.18106060606060603,
              0.176228278958164,
              0.1609609513211208,
              0.18177432004139582,
              0.19621212121212123,
              0.1941728517835775,
              0.1519570707070707
            ]
          },
          "wednesday": {
            "congestionValue": [
              0.14080086580086582,
              0.10340909090909091,
              0.10448232323232325,
              0.09772727272727273,
              0.08636363636363636,
              0.04945764462809918,
              0.023863636363636365,
              0,
              0,
              0,
              0,
              0,
              0.0125,
              0.04581131078224101,
              0.07897727272727273,
              0.09661733615221987,
              0.1038057461406518,
              0.13853726215644818,
              0.1879313973063973,
              0.22045454545454546,
              0.21050084175084172,
              0.17102272727272727,
              0.18352272727272728,
              0.17159090909090907
            ]
          },
          "thursday": {
            "congestionValue": [
              0.1469716494845361,
              0.09157342657342657,
              0.05688920454545454,
              0.036931818181818184,
              0.037500000000000006,
              0.0125,
              0.025,
              0.018750000000000003,
              0.018750000000000003,
              0.0125,
              0,
              0,
              0,
              0.061363636363636356,
              0.09147727272727271,
              0.11524621212121212,
              0.13177272727272726,
              0.16283735795454546,
              0.21250000000000002,
              0.23295454545454547,
              0.21403619528619527,
              0.20254178352372482,
              0.2382806221339763,
              0.2548611111111111
            ]
          },
          "friday": {
            "congestionValue": [
              0.2274802431491199,
              0.14494949494949494,
              0.11577916201676824,
              0.06818181818181819,
              0.05702479338842976,
              0.04832128099173554,
              0.04318181818181818,
              0.025,
              0.0125,
              0,
              0,
              0.023863636363636365,
              0.023863636363636365,
              0.10025252525252526,
              0.1009469696969697,
              0.15397537466164918,
              0.1525252525252525,
              0.19450384675773275,
              0.2097222222222222,
              0.226010101010101,
              0.24839522456709953,
              0.2777777777777778,
              0.3145299145299145,
              0.30833333333333335
            ]
          },
          "saturday": {
            "congestionValue": [
              0.2816132478632478,
              0.24853801169590645,
              0.23333333333333334,
              0.18592105263157893,
              0.1388888888888889,
              0.10432581018518519,
              0.06142139479905438,
              0.0125,
              0,
              0,
              0.0125,
              0.026059941520467835,
              0.05186011904761905,
              0.09526748971193416,
              0.15092592592592596,
              0.2013888888888889,
              0.2178714859437751,
              0.28196373456790125,
              0.3808856310013718,
              0.45937500000000003,
              0.397800925925926,
              0.3205882352941177,
              0.23750000000000002,
              0.1954545454545455
            ]
          }
        }
      },
      "accessHours": {
        "twentyFourSeven": true
      },
      "locationGUID": "c225856c-2b9b-4b77-a028-4cd6d8c678a6",
      "commonSiteName": "Gateway Shopping Center",
      "ownershipType": null,
      "brandName": null,
      "effectivePricebooks": [
        {
          "feeType": "CHARGING",
          "rateBase": 0.47,
          "rateTier1": 0,
          "rateTier2": 0,
          "rateMinTier1": null,
          "rateMinTier2": null,
          "rateMinTier3": null,
          "rateMinTier4": null,
          "currencyCode": "USD",
          "uom": "kwh",
          "startTime": "",
          "endTime": "",
          "days": "",
          "isTou": false,
          "vehicleMakeType": "TSLA",
          "minSiteOccupancy": null,
          "maxSiteOccupancy": null,
          "isMemberPricebook": true
        },
        {
          "feeType": "CONGESTION",
          "rateBase": 0.5,
          "rateTier1": 0,
          "rateTier2": 0,
          "rateMinTier1": null,
          "rateMinTier2": null,
          "rateMinTier3": null,
          "rateMinTier4": null,
          "currencyCode": "USD",
          "uom": "min",
          "startTime": "",
          "endTime": "",
          "days": "",
          "isTou": false,
          "vehicleMakeType": "TSLA",
          "minSiteOccupancy": null,
          "maxSiteOccupancy": null,
          "isMemberPricebook": true
        },
        {
          "feeType": "CHARGING",
          "rateBase": 0.66,
          "rateTier1": 0,
          "rateTier2": 0,
          "rateMinTier1": null,
          "rateMinTier2": null,
          "rateMinTier3": null,
          "rateMinTier4": null,
          "currencyCode": "USD",
          "uom": "kwh",
          "startTime": "",
          "endTime": "",
          "days": "",
          "isTou": false,
          "vehicleMakeType": "NTSLA",
          "minSiteOccupancy": null,
          "maxSiteOccupancy": null,
          "isMemberPricebook": false
        },
        {
          "feeType": "CONGESTION",
          "rateBase": 0.5,
          "rateTier1": 0,
          "rateTier2": 0,
          "rateMinTier1": null,
          "rateMinTier2": null,
          "rateMinTier3": null,
          "rateMinTier4": null,
          "currencyCode": "USD",
          "uom": "min",
          "startTime": "",
          "endTime": "",
          "days": "",
          "isTou": false,
          "vehicleMakeType": "NTSLA",
          "minSiteOccupancy": null,
          "maxSiteOccupancy": null,
          "isMemberPricebook": false
        }
      ],
      "isTrailerFriendly": false
    },
    "success": true
  }
}